README.md
setup.py
fortiori/__init__.py
fortiori/__main__.py
fortiori/edits.py
fortiori/exceptions.py
fortiori/operation.py
fortiori/simple_operations.py
fortiori/transpiler.py
fortiori/type.py
fortiori.egg-info/PKG-INFO
fortiori.egg-info/SOURCES.txt
fortiori.egg-info/dependency_links.txt
fortiori.egg-info/top_level.txt
test/test_simple_operations.py