Metadata-Version: 2.1
Name: fortiori
Version: 0.0.0
Summary: Syntactic sugar for FORTRAN afficionados. (Proof of concept)
Home-page: https://github.com/keotl/fortiori
Author: Kento A. Lauzon
Author-email: kento.lauzon@ligature.ca
License: UNKNOWN
Platform: UNKNOWN
Classifier: Development Status :: 3 - Alpha
Classifier: Intended Audience :: Developers
Classifier: Topic :: Software Development :: Code Generators
Classifier: License :: OSI Approved :: MIT License
Classifier: Programming Language :: Python :: 3.6
Classifier: Programming Language :: Python :: 3.7
